mdx_code-0.1.0.dist-info/licenses/LICENSE
mdxcode/__init__.py
mdxcode/cli.py
mdxcode/core/__init__.py
mdxcode/core/agent_loop.py
mdxcode/core/context_loader.py
mdxcode/core/session.py
mdxcode/governance/__init__.py
mdxcode/governance/audit.py
mdxcode/governance/permissions.py
mdxcode/governance/security_agent.py
mdxcode/models/__init__.py
mdxcode/models/auth.py
mdxcode/models/router.py
mdxcode/tools/__init__.py
mdxcode/tools/registry.py
mdx_code-0.1.0.dist-info/METADATA
mdx_code-0.1.0.dist-info/WHEEL
mdx_code-0.1.0.dist-info/entry_points.txt
mdx_code-0.1.0.dist-info/top_level.txt
mdx_code-0.1.0.dist-info/RECORD
