Metadata-Version: 2.4
Name: mdx-code
Version: 0.1.0
Summary: AI-Native Engineering Companion. Built for builders. Designed for regulated environments.
Author: MD
License: MIT
Project-URL: Homepage, https://github.com/dhotherm/mdx-code
Project-URL: Documentation, https://github.com/dhotherm/mdx-code#readme
Project-URL: Repository, https://github.com/dhotherm/mdx-code
Project-URL: Issues, https://github.com/dhotherm/mdx-code/issues
Keywords: ai,llm,claude,developer-tools,agents,agentic-ai,code-assistant
Classifier: Development Status :: 4 - Beta
Classifier: Environment :: Console
Classifier: Intended Audience :: Developers
Classifier: License :: OSI Approved :: MIT License
Classifier: Operating System :: OS Independent
Classifier: Programming Language :: Python :: 3
Classifier: Programming Language :: Python :: 3.9
Classifier: Programming Language :: Python :: 3.10
Classifier: Programming Language :: Python :: 3.11
Classifier: Programming Language :: Python :: 3.12
Classifier: Topic :: Software Development
Classifier: Topic :: Software Development :: Code Generators
Requires-Python: >=3.9
License-File: LICENSE
Requires-Dist: anthropic>=0.40.0
Requires-Dist: httpx>=0.27.0
Requires-Dist: pydantic>=2.0.0
Requires-Dist: typer>=0.12.0
Requires-Dist: rich>=13.0.0
Requires-Dist: pyyaml>=6.0
Requires-Dist: python-dotenv>=1.0.0
Provides-Extra: dev
Requires-Dist: pytest>=8.0.0; extra == "dev"
Requires-Dist: pytest-asyncio>=0.23.0; extra == "dev"
Requires-Dist: black>=24.0.0; extra == "dev"
Requires-Dist: mypy>=1.8.0; extra == "dev"
Provides-Extra: openai
Requires-Dist: openai>=1.0.0; extra == "openai"
Provides-Extra: bedrock
Requires-Dist: boto3>=1.34.0; extra == "bedrock"
Provides-Extra: all
Requires-Dist: openai>=1.0.0; extra == "all"
Requires-Dist: boto3>=1.34.0; extra == "all"
Requires-Dist: google-cloud-aiplatform>=1.0.0; extra == "all"
Dynamic: license-file
